exceptions/__init__.py
exceptions/exceptions.py
mc_protocol/__init__.py
mc_protocol/mc_client.py
mc_protocol/network/__init__.py
mc_protocol/network/game/__init__.py
mc_protocol/network/game/packet.py
mc_protocol/network/game/packet_ids.py
mc_protocol/network/game/packets/__init__.py
mc_protocol/network/game/packets/chunkdata/chunk_data.py
mc_protocol/network/game/packets/login/C2MojangSession.py
mc_protocol/network/game/packets/login/C2SEncryptionResponse.py
mc_protocol/network/game/packets/login/C2SLoginStartPacket.py
mc_protocol/network/game/packets/login/S2CEncryptionRequest.py
mc_protocol/network/game/packets/login/S2CLoginSuccess.py
mc_protocol/network/game/packets/login/S2CSetCompression.py
mc_protocol/network/game/packets/login/__init__.py
mc_protocol/network/game/packets/playerdigging/player_digging.py
mc_protocol/network/game/packets/playerposition/player_pos_and_look.py
mc_protocol/network/game/packets/playerposition/player_position.py
mc_protocol/network/oauth/__init__.py
mc_protocol/network/oauth/oauth.py
mc_protocol/network/oauth/redirect_server.py
mc_protocol/network/packet/__init__.py
mc_protocol/network/packet/packet_encryptor.py
mc_protocol/network/packet/varint_processor.py
mc_protocol/network/ping/__init__.py
mc_protocol/network/ping/modern_pinger.py
mc_protocol/network/ping/old_pinger.py
mc_protocol/network/ping/pinger.py
utils/__init__.py
utils/color.py
utils/player_utils.py
utils/version/__init__.py
utils/version/manifest_version.py
utils/version/protocol_versions.py
utils/version/version.py
mc_protocol-1.0.3.dist-info/METADATA
mc_protocol-1.0.3.dist-info/WHEEL
mc_protocol-1.0.3.dist-info/top_level.txt
mc_protocol-1.0.3.dist-info/RECORD
